rentCalculations/__init__.py
rentCalculations/calculate.py
rentalUtility-0.1.0.dist-info/LICENSE
rentalUtility-0.1.0.dist-info/METADATA
rentalUtility-0.1.0.dist-info/WHEEL
rentalUtility-0.1.0.dist-info/top_level.txt
rentalUtility-0.1.0.dist-info/RECORD
